COPYING
MANIFEST.in
README.md
setup.py
pywidl/__init__.py
pywidl/grammar.py
pywidl/helper.py
pywidl/lexis.py
pywidl/model.py
pywidl/parsetab.py
pywidl/pywidl.py
pywidl.egg-info/PKG-INFO
pywidl.egg-info/SOURCES.txt
pywidl.egg-info/dependency_links.txt
pywidl.egg-info/entry_points.txt
pywidl.egg-info/requires.txt
pywidl.egg-info/top_level.txt
tests/__init__.py
tests/idl.py
tests/test_suite.py