Metadata-Version: 1.0
Name: pywidl
Version: 0.1
Summary: Generic code generator from WebIDL interfaces.
Home-page: https://github.com/VasilyStepanov/pywidl
Author: Vasily Stepanov
Author-email: vasily.stepanov@gmail.com
License: MIT
Keywords: webidl
Platform: UNKNOWN
Classifier: Development Status :: 3 - Alpha
Classifier: Topic :: Software Development :: Code Generators
Classifier: License :: OSI Approved :: MIT License
